polipy/__init__.py
polipy/__main__.py
polipy/constants.py
polipy/exceptions.py
polipy/extractors.py
polipy/logger.py
polipy/networking.py
polipy/polipy.py
polipy/scraper.py
polipy-0.1.4.dist-info/LICENSE
polipy-0.1.4.dist-info/METADATA
polipy-0.1.4.dist-info/WHEEL
polipy-0.1.4.dist-info/entry_points.txt
polipy-0.1.4.dist-info/top_level.txt
polipy-0.1.4.dist-info/RECORD
