Metadata-Version: 2.1
Name: polipy
Version: 0.1.4
Summary: Library for scraping, parsing, and analyzing privacy policies.
Home-page: https://github.com/blues-lab/polipy
Author: Berkeley Lab for Usable and Experimental Security (BLUES)
Author-email: blues@berkeley.edu
License: GNU General Public License v3.0 (GPLv3)
Classifier: License :: OSI Approved :: GNU General Public License v3 (GPLv3)
Classifier: Programming Language :: Python :: 3
Classifier: Programming Language :: Python :: 3.9
License-File: LICENSE
